LICENSE
README.md
setup.py
Aminopy.egg-info/PKG-INFO
Aminopy.egg-info/SOURCES.txt
Aminopy.egg-info/dependency_links.txt
Aminopy.egg-info/requires.txt
Aminopy.egg-info/top_level.txt
amino/__init__.py
amino/acm.py
amino/client.py
amino/socket.py
amino/sub_client.py
amino/src/__init__.py
amino/src/device.py
amino/src/exceptions.py
amino/src/headers.py
amino/src/helpers.py
amino/src/objects.py
amino/src/voice_header.py