Metadata-Version: 2.1
Name: Aminopy
Version: 1.0.0
Summary: A library to create Amino bots.
Home-page: https://github.com/Oustex/Aminopy
Author: Oustex
Author-email: oustexp@gmail.com
License: Apache V2
Download-URL: https://github.com/Oustex/Aminopy/tarball/master
Keywords: aminoapps,amino-py,amino,amino-bot,narvii,api,oustex,slimakoi,aminopy,official
Platform: UNKNOWN
License-File: LICENSE
